src/h264_encoder/__init__.py
src/h264_encoder/converter
src/h264_encoder/encoder.py
py_h264_encoder-0.1.0.dist-info/METADATA
py_h264_encoder-0.1.0.dist-info/WHEEL
py_h264_encoder-0.1.0.dist-info/licenses/LICENSE
py_h264_encoder-0.1.0.dist-info/RECORD
