Metadata-Version: 2.4
Name: py-h264-encoder
Version: 0.1.0
Summary: A Python library for encoding videos to H.264.
Project-URL: Documentation, https://github.com/orphanbyte/py-h264-encoder
Project-URL: Source, https://github.com/orphanbyte/py-h264-encoder
Project-URL: Issues, https://github.com/orphanbyte/py-h264-encoder/issues
Author-email: Orphan Byte <orphanbyte@proton.me>
License: MIT License
License-File: LICENSE
Classifier: Development Status :: 4 - Beta
Classifier: Intended Audience :: Developers
Classifier: License :: OSI Approved :: MIT License
Classifier: Operating System :: POSIX :: Linux
Classifier: Programming Language :: Python :: 3
Classifier: Topic :: Multimedia :: Video :: Conversion
